env.sh
run
setup.cfg
setup.py
commerce/__init__.py
commerce/basket.py
commerce.egg-info/PKG-INFO
commerce.egg-info/SOURCES.txt
commerce.egg-info/dependency_links.txt
commerce.egg-info/entry_points.txt
commerce.egg-info/top_level.txt
commerce.egg-info/zip-safe
commerce/old/basket.py
commerce/old/baskethelper.py
commerce/old/basketpage.py
commerce/old/cbasket.py
commerce/tests/test_basket.py