Metadata-Version: 1.0
Name: commerce
Version: 0.1dev
Summary: Generic shopping basket
Home-page: http://ish.io
Author: Tim Parkin
Author-email: ish@ish.io
License: UNKNOWN
Platform: UNKNOWN
